mcc_f1/__init__.py
mcc_f1/mcc_f1_curve.py
mcc_f1/_plot/__init__.py
mcc_f1/_plot/base.py
mcc_f1/_plot/mcc_f1_curve.py
py_mcc_f1-0.1.0.dist-info/LICENSE
py_mcc_f1-0.1.0.dist-info/METADATA
py_mcc_f1-0.1.0.dist-info/WHEEL
py_mcc_f1-0.1.0.dist-info/top_level.txt
py_mcc_f1-0.1.0.dist-info/RECORD
