Metadata-Version: 2.1
Name: py-mcc-f1
Version: 0.1.0
Summary: MCC-F1 Curve
Home-page: https://github.com/arthurcgusmao/py-mcc-f1
Author: Arthur Colombini Gusmão
License: UNKNOWN
Platform: UNKNOWN
Classifier: Programming Language :: Python :: 3
Classifier: License :: OSI Approved :: MIT License
Classifier: Operating System :: OS Independent
Requires-Python: >=3.6
Requires-Dist: numpy (>=1.14.0)
Requires-Dist: scikit-learn (>=0.22)
